{"cameraMode":{"drawMode":0,"name":"Shaded","section":"Shading Mode"},"sceneLighting":true,"audioPlay":false,"sceneViewState":{"showFog":true,"showMaterialUpdate":false,"showSkybox":true,"showFlares":true,"showImageEffects":true,"showParticleSystems":true},"in2DMode":false,"pivot":{"x":-0.574648916721344,"y":2.7988452911376955,"z":1.7395899295806885},"rotation":{"x":0.06752832233905792,"y":0.8950525522232056,"z":-0.14518308639526368,"w":0.4162440001964569},"size":10.44839096069336,"orthographic":false}